{
  "catalog_info": {
    "academic_year": "2022-2026",
    "institution": "Mount San Antonio College"
  },
  "total_courses": 15,
  "courses": [
    {
      "department_code": "DN-T",
      "course_number": "20",
      "title": "Hist-Appreciati",
      "units": "3.00",
      "department": "",
      "description": "Hist-Appreciati",
      "enhanced_description": "Hist-Appreciati"
    },
    {
      "department_code": "MATH",
      "course_number": "110",
      "title": "Elementary Stat",
      "units": "3.00",
      "department": "",
      "description": "Elementary Stat",
      "enhanced_description": "Elementary Stat"
    },
    {
      "department_code": "SOC",
      "course_number": "1",
      "title": "Introduction to",
      "units": "3.00",
      "department": "",
      "description": "Introduction to Web Site Develo",
      "enhanced_description": "Introduction to"
    },
    {
      "department_code": "SIGN",
      "course_number": "101",
      "title": "American Sign L",
      "units": "4.00",
      "department": "",
      "description": "American Sign L History of US t",
      "enhanced_description": "American Sign L"
    },
    {
      "department_code": "LCOM",
      "course_number": "80",
      "title": "LCOM: Indiv Con",
      "units": "1.00",
      "department": "",
      "description": "LCOM: Indiv Con Public Speaking",
      "enhanced_description": "LCOM: Indiv Con"
    },
    {
      "department_code": "ASTR",
      "course_number": "5",
      "title": "Intro to Astronomy",
      "units": "3.00",
      "department": "",
      "description": "Intro to Astronomy",
      "enhanced_description": "Intro to Astronomy"
    },
    {
      "department_code": "ENGL",
      "course_number": "1C",
      "title": "Critical Thinking&Writing",
      "units": "4.00",
      "department": "",
      "description": "Critical Thinking&Writing",
      "enhanced_description": "Critical Thinking&Writing"
    },
    {
      "department_code": "HIST",
      "course_number": "8",
      "title": "History of US from 1865",
      "units": "3.00",
      "department": "",
      "description": "History of US from 1865",
      "enhanced_description": "History of US from 1865"
    },
    {
      "department_code": "KINI",
      "course_number": "33A",
      "title": "Kickboxing Beginning",
      "units": "1.00",
      "department": "",
      "description": "Kickboxing Beginning",
      "enhanced_description": "Kickboxing Beginning"
    },
    {
      "department_code": "KINI",
      "course_number": "4A",
      "title": "Badminton - Beginning",
      "units": "1.00",
      "department": "",
      "description": "Badminton - Beginning",
      "enhanced_description": "Badminton - Beginning"
    },
    {
      "department_code": "AHIS",
      "course_number": "5",
      "title": "Art History Ren",
      "units": "3.00",
      "department": "",
      "description": "Art History Ren Intro Human Ana",
      "enhanced_description": "Art History Ren"
    },
    {
      "department_code": "ENGL",
      "course_number": "1A",
      "title": "Freshman Compos",
      "units": "4.00",
      "department": "",
      "description": "Freshman Compos Intro to Kinesi",
      "enhanced_description": "Freshman Compos"
    },
    {
      "department_code": "KIN",
      "course_number": "3",
      "title": "First Aid & CPR",
      "units": "3.00",
      "department": "",
      "description": "First Aid & CPR",
      "enhanced_description": "First Aid & CPR"
    },
    {
      "department_code": "KINS",
      "course_number": "24A",
      "title": "Volleyball - Beginning",
      "units": "0.50",
      "department": "",
      "description": "Volleyball - Beginning",
      "enhanced_description": "Volleyball - Beginning"
    },
    {
      "department_code": "KIN",
      "course_number": "34",
      "title": "Fitness for Liv",
      "units": "3.00",
      "department": "",
      "description": "Fitness for Liv Intro Human Phy",
      "enhanced_description": "Fitness for Liv"
    }
  ]
}